aio_check/__init__.py
aio_check/check.py
AIO_CodeCheck-0.5.dist-info/LICENSE
AIO_CodeCheck-0.5.dist-info/METADATA
AIO_CodeCheck-0.5.dist-info/WHEEL
AIO_CodeCheck-0.5.dist-info/entry_points.txt
AIO_CodeCheck-0.5.dist-info/top_level.txt
AIO_CodeCheck-0.5.dist-info/RECORD
